<annotation>
	<folder>Images</folder>
	<filename>44.jpg</filename>
	<path>/home/hussam/Desktop/Project/Images/44.jpg</path>
	<source>
		<database>Unknown</database>
	</source>
	<size>
		<width>900</width>
		<height>900</height>
		<depth>3</depth>
	</size>
	<segmented>0</segmented>
	<object>
		<name>tip</name>
		<pose>Unspecified</pose>
		<truncated>0</truncated>
		<difficult>0</difficult>
		<bndbox>
			<xmin>312</xmin>
			<ymin>411</ymin>
			<xmax>355</xmax>
			<ymax>448</ymax>
		</bndbox>
	</object>
	<object>
		<name>tip</name>
		<pose>Unspecified</pose>
		<truncated>0</truncated>
		<difficult>0</difficult>
		<bndbox>
			<xmin>457</xmin>
			<ymin>496</ymin>
			<xmax>502</xmax>
			<ymax>532</ymax>
		</bndbox>
	</object>
	<object>
		<name>tip</name>
		<pose>Unspecified</pose>
		<truncated>0</truncated>
		<difficult>0</difficult>
		<bndbox>
			<xmin>418</xmin>
			<ymin>421</ymin>
			<xmax>472</xmax>
			<ymax>468</ymax>
		</bndbox>
	</object>
	<object>
		<name>tip</name>
		<pose>Unspecified</pose>
		<truncated>0</truncated>
		<difficult>0</difficult>
		<bndbox>
			<xmin>424</xmin>
			<ymin>325</ymin>
			<xmax>468</xmax>
			<ymax>370</ymax>
		</bndbox>
	</object>
	<object>
		<name>tip</name>
		<pose>Unspecified</pose>
		<truncated>0</truncated>
		<difficult>0</difficult>
		<bndbox>
			<xmin>489</xmin>
			<ymin>333</ymin>
			<xmax>530</xmax>
			<ymax>383</ymax>
		</bndbox>
	</object>
</annotation>
