<annotation>
	<folder>Images</folder>
	<filename>99.jpg</filename>
	<path>/home/hussam/Desktop/Project/Images/99.jpg</path>
	<source>
		<database>Unknown</database>
	</source>
	<size>
		<width>900</width>
		<height>900</height>
		<depth>3</depth>
	</size>
	<segmented>0</segmented>
	<object>
		<name>tip</name>
		<pose>Unspecified</pose>
		<truncated>0</truncated>
		<difficult>0</difficult>
		<bndbox>
			<xmin>224</xmin>
			<ymin>338</ymin>
			<xmax>270</xmax>
			<ymax>371</ymax>
		</bndbox>
	</object>
	<object>
		<name>tip</name>
		<pose>Unspecified</pose>
		<truncated>0</truncated>
		<difficult>0</difficult>
		<bndbox>
			<xmin>250</xmin>
			<ymin>238</ymin>
			<xmax>306</xmax>
			<ymax>284</ymax>
		</bndbox>
	</object>
	<object>
		<name>tip</name>
		<pose>Unspecified</pose>
		<truncated>0</truncated>
		<difficult>0</difficult>
		<bndbox>
			<xmin>330</xmin>
			<ymin>197</ymin>
			<xmax>391</xmax>
			<ymax>249</ymax>
		</bndbox>
	</object>
	<object>
		<name>tip</name>
		<pose>Unspecified</pose>
		<truncated>0</truncated>
		<difficult>0</difficult>
		<bndbox>
			<xmin>471</xmin>
			<ymin>384</ymin>
			<xmax>536</xmax>
			<ymax>427</ymax>
		</bndbox>
	</object>
	<object>
		<name>tip</name>
		<pose>Unspecified</pose>
		<truncated>0</truncated>
		<difficult>0</difficult>
		<bndbox>
			<xmin>570</xmin>
			<ymin>347</ymin>
			<xmax>636</xmax>
			<ymax>378</ymax>
		</bndbox>
	</object>
</annotation>
